{"pageContext":{"frontmatter":{"name":"Workouts","menu":"SCREENS"},"entry":{"id":"6a572e9925506c1d7b70e78ca8e68db1","filepath":"src/screens/workouts/workouts.mdx","fullpath":"/Users/rafaeldiaz/Documents/development/lanista-workout/src/screens/workouts/workouts.mdx","route":"/src-screens-workouts-workouts","slug":"src-screens-workouts-workouts","name":"Workouts","menu":"SCREENS","headings":[{"slug":"workouts-view-component","depth":1,"value":"Workouts View Component"},{"slug":"beschreibung","depth":2,"value":"Beschreibung"}]}}}